<VOTABLE version='1.1' xmlns="http://www.ivoa.net/xml/VOTable/v1.1">
<RESOURCE>
<DESCRIPTION></DESCRIPTION>
<INFO name="QUERY_STATUS" value="OK"/>
<INFO name="EXECUTED_AT" value="2014-03-19 11:24:44"/>
<INFO name="MAX_RECORD_ALLOWED" value="20000"/>
<INFO name="QUERY_STRING" ><![CDATA[SELECT soho_lasco_cme.HEC_id,soho_lasco_cme.time_start,soho_lasco_cme.pa,soho_lasco_cme.pa_width,soho_lasco_cme.v,soho_lasco_cme.v_init,soho_lasco_cme.v_final,soho_lasco_cme.v_20r,soho_lasco_cme.accel,soho_lasco_cme.pa_measure FROM soho_lasco_cme WHERE  time_start>='2004-04-01 00:00:00' AND time_start<='2004-04-30 23:59:59'    LIMIT 20000]]></INFO>
<INFO name="QUERY_URL" ><![CDATA[http://msslkz.mssl.ucl.ac.uk:80/helio-hec/HelioQueryService?STARTTIME=2004-04-01 00:00:00&ENDTIME=2004-04-30 23:59:59&FROM=soho_lasco_cme]]></INFO>
<INFO name="TABLE_NAME" value="soho_lasco_cme"/><TABLE name="hec-soho_lasco_cme">
<FIELD datatype="int" name="hec_id" ucd="meta.record">
<DESCRIPTION>Event identification number (HEC internal number)</DESCRIPTION>
<VALUES null='-2147483648'/>
</FIELD>
<FIELD arraysize="*" datatype="char" name="time_start" ucd="time.start" utype="helio:time_period.time_start" xtype="iso8601">
<DESCRIPTION>Start time - the time of first appearance in the LASCO/C2 field of view.</DESCRIPTION>
</FIELD>
<FIELD datatype="float" name="pa" ucd="pos.posAng" utype="helio:location.pa">
<DESCRIPTION>Central position angle for the CME</DESCRIPTION>
</FIELD>
<FIELD datatype="float" name="pa_width" ucd="pos.posAng;phys.angSize" utype="helio:location.pa_measure">
<DESCRIPTION>Position angle width of the CME</DESCRIPTION>
</FIELD>
<FIELD datatype="float" name="v" ucd="pos.posAng;phys.angSize" utype="helio:location.pa_width">
<DESCRIPTION>the linear speed obtained by fitting a straight line to the height-time measurements made at the fastest section of CMEs</DESCRIPTION>
</FIELD>
<FIELD datatype="float" name="v_init" ucd="phys.veloc" utype="helio:cme.velocity.v">
<DESCRIPTION>quadratic speed obtained by fitting a parabola and evaluating the speed at the initial time of the event</DESCRIPTION>
</FIELD>
<FIELD datatype="float" name="v_final" ucd="phys.veloc" utype="helio:cme.velocity.v_init">
<DESCRIPTION>quadratic speed obtained by fitting a parabola and evaluating the speed at the time of final height measurement</DESCRIPTION>
</FIELD>
<FIELD datatype="float" name="v_20r" ucd="phys.veloc" utype="helio:cme.velocity.v_final">
<DESCRIPTION>quadratic speed obtained by fitting a parabola and evaluating the speed at 20 solar radii</DESCRIPTION>
</FIELD>
<FIELD datatype="float" name="accel" ucd="phys.veloc" utype="helio:cme.velocity.v_20r">
<DESCRIPTION>Acceleration is obtained from the quadratic fit to the height-time measurements</DESCRIPTION>
</FIELD>
<FIELD datatype="float" name="pa_measure" ucd="phys.acceleration" utype="helio:cme.acceleration">
<DESCRIPTION>The position angle at which the height-time measurements are made (MPA for measurement position angle).</DESCRIPTION>
</FIELD>
<DATA>
<TABLEDATA>
  <TR>
    <TD>8593</TD>
    <TD>2004-04-01T22:00:05</TD>
    <TD>59.0</TD>
    <TD>79.0</TD>
    <TD>460.0</TD>
    <TD>325.0</TD>
    <TD>613.0</TD>
    <TD>528.0</TD>
    <TD>7.1</TD>
    <TD>54.0</TD>
  </TR>
  <TR>
    <TD>8594</TD>
    <TD>2004-04-02T03:00:05</TD>
    <TD>128.0</TD>
    <TD>25.0</TD>
    <TD>405.0</TD>
    <TD>486.0</TD>
    <TD>321.0</TD>
    <TD>0.0</TD>
    <TD>-33.1</TD>
    <TD>126.0</TD>
  </TR>
  <TR>
    <TD>8595</TD>
    <TD>2004-04-02T11:00:05</TD>
    <TD>56.0</TD>
    <TD>34.0</TD>
    <TD>84.0</TD>
    <TD>75.0</TD>
    <TD>92.0</TD>
    <TD>229.0</TD>
    <TD>2.0</TD>
    <TD>60.0</TD>
  </TR>
  <TR>
    <TD>8596</TD>
    <TD>2004-04-02T23:40:06</TD>
    <TD>246.0</TD>
    <TD>38.0</TD>
    <TD>304.0</TD>
    <TD>347.0</TD>
    <TD>263.0</TD>
    <TD>0.0</TD>
    <TD>-7.1</TD>
    <TD>247.0</TD>
  </TR>
  <TR>
    <TD>8597</TD>
    <TD>2004-04-03T04:00:06</TD>
    <TD>250.0</TD>
    <TD>41.0</TD>
    <TD>341.0</TD>
    <TD>353.0</TD>
    <TD>328.0</TD>
    <TD>308.0</TD>
    <TD>-1.3</TD>
    <TD>254.0</TD>
  </TR>
  <TR>
    <TD>8598</TD>
    <TD>2004-04-03T11:00:05</TD>
    <TD>122.0</TD>
    <TD>50.0</TD>
    <TD>458.0</TD>
    <TD>543.0</TD>
    <TD>374.0</TD>
    <TD>282.0</TD>
    <TD>-9.1</TD>
    <TD>118.0</TD>
  </TR>
  <TR>
    <TD>8599</TD>
    <TD>2004-04-03T23:20:05</TD>
    <TD>127.0</TD>
    <TD>34.0</TD>
    <TD>374.0</TD>
    <TD>452.0</TD>
    <TD>297.0</TD>
    <TD>0.0</TD>
    <TD>-32.5</TD>
    <TD>121.0</TD>
  </TR>
  <TR>
    <TD>8600</TD>
    <TD>2004-04-04T00:20:06</TD>
    <TD>135.0</TD>
    <TD>22.0</TD>
    <TD>426.0</TD>
    <TD>329.0</TD>
    <TD>525.0</TD>
    <TD>950.0</TD>
    <TD>32.7</TD>
    <TD>137.0</TD>
  </TR>
  <TR>
    <TD>8601</TD>
    <TD>2004-04-04T01:20:05</TD>
    <TD>128.0</TD>
    <TD>47.0</TD>
    <TD>445.0</TD>
    <TD>530.0</TD>
    <TD>362.0</TD>
    <TD>97.0</TD>
    <TD>-11.6</TD>
    <TD>121.0</TD>
  </TR>
  <TR>
    <TD>8602</TD>
    <TD>2004-04-04T12:20:05</TD>
    <TD>131.0</TD>
    <TD>29.0</TD>
    <TD>360.0</TD>
    <TD>244.0</TD>
    <TD>477.0</TD>
    <TD>1006.0</TD>
    <TD>39.3</TD>
    <TD>132.0</TD>
  </TR>
  <TR>
    <TD>8603</TD>
    <TD>2004-04-04T16:00:05</TD>
    <TD>131.0</TD>
    <TD>53.0</TD>
    <TD>520.0</TD>
    <TD>420.0</TD>
    <TD>630.0</TD>
    <TD>713.0</TD>
    <TD>13.8</TD>
    <TD>141.0</TD>
  </TR>
  <TR>
    <TD>8604</TD>
    <TD>2004-04-05T01:31:44</TD>
    <TD>273.0</TD>
    <TD>13.0</TD>
    <TD>776.0</TD>
    <TD>979.0</TD>
    <TD>554.0</TD>
    <TD>0.0</TD>
    <TD>-206.2</TD>
    <TD>276.0</TD>
  </TR>
  <TR>
    <TD>8605</TD>
    <TD>2004-04-05T02:54:05</TD>
    <TD>112.0</TD>
    <TD>41.0</TD>
    <TD>431.0</TD>
    <TD>418.0</TD>
    <TD>443.0</TD>
    <TD>492.0</TD>
    <TD>2.9</TD>
    <TD>118.0</TD>
  </TR>
  <TR>
    <TD>8606</TD>
    <TD>2004-04-05T05:06:06</TD>
    <TD>124.0</TD>
    <TD>51.0</TD>
    <TD>507.0</TD>
    <TD>529.0</TD>
    <TD>485.0</TD>
    <TD>269.0</TD>
    <TD>-8.8</TD>
    <TD>116.0</TD>
  </TR>
  <TR>
    <TD>8607</TD>
    <TD>2004-04-05T06:06:05</TD>
    <TD>111.0</TD>
    <TD>191.0</TD>
    <TD>608.0</TD>
    <TD>717.0</TD>
    <TD>496.0</TD>
    <TD>528.0</TD>
    <TD>-9.7</TD>
    <TD>125.0</TD>
  </TR>
  <TR>
    <TD>8608</TD>
    <TD>2004-04-05T21:08:03</TD>
    <TD>111.0</TD>
    <TD>27.0</TD>
    <TD>376.0</TD>
    <TD>353.0</TD>
    <TD>399.0</TD>
    <TD>404.0</TD>
    <TD>1.6</TD>
    <TD>108.0</TD>
  </TR>
  <TR>
    <TD>8609</TD>
    <TD>2004-04-06T00:30:05</TD>
    <TD>247.0</TD>
    <TD>17.0</TD>
    <TD>427.0</TD>
    <TD>382.0</TD>
    <TD>471.0</TD>
    <TD>678.0</TD>
    <TD>13.3</TD>
    <TD>249.0</TD>
  </TR>
  <TR>
    <TD>8610</TD>
    <TD>2004-04-06T02:54:05</TD>
    <TD>106.0</TD>
    <TD>14.0</TD>
    <TD>339.0</TD>
    <TD>192.0</TD>
    <TD>491.0</TD>
    <TD>865.0</TD>
    <TD>30.0</TD>
    <TD>109.0</TD>
  </TR>
  <TR>
    <TD>8611</TD>
    <TD>2004-04-06T13:31:43</TD>
    <TD>-1.0</TD>
    <TD>360.0</TD>
    <TD>1368.0</TD>
    <TD>1123.0</TD>
    <TD>1625.0</TD>
    <TD>1511.0</TD>
    <TD>45.6</TD>
    <TD>167.0</TD>
  </TR>
  <TR>
    <TD>8612</TD>
    <TD>2004-04-06T20:06:06</TD>
    <TD>177.0</TD>
    <TD>76.0</TD>
    <TD>367.0</TD>
    <TD>391.0</TD>
    <TD>343.0</TD>
    <TD>267.0</TD>
    <TD>-3.5</TD>
    <TD>186.0</TD>
  </TR>
  <TR>
    <TD>8613</TD>
    <TD>2004-04-07T15:30:34</TD>
    <TD>247.0</TD>
    <TD>36.0</TD>
    <TD>327.0</TD>
    <TD>296.0</TD>
    <TD>362.0</TD>
    <TD>376.0</TD>
    <TD>2.3</TD>
    <TD>257.0</TD>
  </TR>
  <TR>
    <TD>8614</TD>
    <TD>2004-04-07T21:54:05</TD>
    <TD>275.0</TD>
    <TD>39.0</TD>
    <TD>149.0</TD>
    <TD>125.0</TD>
    <TD>173.0</TD>
    <TD>416.0</TD>
    <TD>6.6</TD>
    <TD>282.0</TD>
  </TR>
  <TR>
    <TD>8615</TD>
    <TD>2004-04-08T02:06:05</TD>
    <TD>279.0</TD>
    <TD>113.0</TD>
    <TD>319.0</TD>
    <TD>322.0</TD>
    <TD>316.0</TD>
    <TD>313.0</TD>
    <TD>-0.2</TD>
    <TD>276.0</TD>
  </TR>
  <TR>
    <TD>8616</TD>
    <TD>2004-04-08T02:54:06</TD>
    <TD>77.0</TD>
    <TD>11.0</TD>
    <TD>387.0</TD>
    <TD>437.0</TD>
    <TD>334.0</TD>
    <TD>291.0</TD>
    <TD>-4.5</TD>
    <TD>77.0</TD>
  </TR>
  <TR>
    <TD>8617</TD>
    <TD>2004-04-08T04:06:05</TD>
    <TD>73.0</TD>
    <TD>26.0</TD>
    <TD>454.0</TD>
    <TD>452.0</TD>
    <TD>456.0</TD>
    <TD>458.0</TD>
    <TD>0.3</TD>
    <TD>77.0</TD>
  </TR>
  <TR>
    <TD>8618</TD>
    <TD>2004-04-08T06:30:05</TD>
    <TD>272.0</TD>
    <TD>51.0</TD>
    <TD>214.0</TD>
    <TD>175.0</TD>
    <TD>252.0</TD>
    <TD>431.0</TD>
    <TD>6.5</TD>
    <TD>264.0</TD>
  </TR>
  <TR>
    <TD>8619</TD>
    <TD>2004-04-08T10:30:19</TD>
    <TD>-1.0</TD>
    <TD>360.0</TD>
    <TD>1068.0</TD>
    <TD>1320.0</TD>
    <TD>812.0</TD>
    <TD>945.0</TD>
    <TD>-36.5</TD>
    <TD>197.0</TD>
  </TR>
  <TR>
    <TD>8620</TD>
    <TD>2004-04-08T11:30:05</TD>
    <TD>269.0</TD>
    <TD>57.0</TD>
    <TD>335.0</TD>
    <TD>305.0</TD>
    <TD>364.0</TD>
    <TD>480.0</TD>
    <TD>5.7</TD>
    <TD>258.0</TD>
  </TR>
  <TR>
    <TD>8621</TD>
    <TD>2004-04-08T13:31:42</TD>
    <TD>198.0</TD>
    <TD>92.0</TD>
    <TD>959.0</TD>
    <TD>964.0</TD>
    <TD>953.0</TD>
    <TD>956.0</TD>
    <TD>-0.7</TD>
    <TD>202.0</TD>
  </TR>
  <TR>
    <TD>8622</TD>
    <TD>2004-04-08T18:54:05</TD>
    <TD>269.0</TD>
    <TD>62.0</TD>
    <TD>258.0</TD>
    <TD>300.0</TD>
    <TD>215.0</TD>
    <TD>0.0</TD>
    <TD>-5.2</TD>
    <TD>253.0</TD>
  </TR>
  <TR>
    <TD>8623</TD>
    <TD>2004-04-08T20:06:05</TD>
    <TD>101.0</TD>
    <TD>60.0</TD>
    <TD>198.0</TD>
    <TD>222.0</TD>
    <TD>174.0</TD>
    <TD>0.0</TD>
    <TD>-3.7</TD>
    <TD>113.0</TD>
  </TR>
  <TR>
    <TD>8624</TD>
    <TD>2004-04-09T04:30:07</TD>
    <TD>55.0</TD>
    <TD>52.0</TD>
    <TD>297.0</TD>
    <TD>375.0</TD>
    <TD>212.0</TD>
    <TD>0.0</TD>
    <TD>-7.4</TD>
    <TD>62.0</TD>
  </TR>
  <TR>
    <TD>8625</TD>
    <TD>2004-04-09T09:54:05</TD>
    <TD>103.0</TD>
    <TD>42.0</TD>
    <TD>168.0</TD>
    <TD>175.0</TD>
    <TD>159.0</TD>
    <TD>0.0</TD>
    <TD>-1.7</TD>
    <TD>114.0</TD>
  </TR>
  <TR>
    <TD>8626</TD>
    <TD>2004-04-09T12:30:05</TD>
    <TD>251.0</TD>
    <TD>27.0</TD>
    <TD>281.0</TD>
    <TD>260.0</TD>
    <TD>302.0</TD>
    <TD>384.0</TD>
    <TD>3.6</TD>
    <TD>249.0</TD>
  </TR>
  <TR>
    <TD>8627</TD>
    <TD>2004-04-09T12:54:05</TD>
    <TD>122.0</TD>
    <TD>17.0</TD>
    <TD>473.0</TD>
    <TD>406.0</TD>
    <TD>537.0</TD>
    <TD>790.0</TD>
    <TD>20.3</TD>
    <TD>119.0</TD>
  </TR>
  <TR>
    <TD>8628</TD>
    <TD>2004-04-09T20:30:05</TD>
    <TD>227.0</TD>
    <TD>273.0</TD>
    <TD>977.0</TD>
    <TD>1000.0</TD>
    <TD>955.0</TD>
    <TD>959.0</TD>
    <TD>-3.3</TD>
    <TD>215.0</TD>
  </TR>
  <TR>
    <TD>8629</TD>
    <TD>2004-04-10T00:54:05</TD>
    <TD>227.0</TD>
    <TD>32.0</TD>
    <TD>606.0</TD>
    <TD>598.0</TD>
    <TD>612.0</TD>
    <TD>616.0</TD>
    <TD>0.9</TD>
    <TD>225.0</TD>
  </TR>
  <TR>
    <TD>8630</TD>
    <TD>2004-04-10T02:08:05</TD>
    <TD>272.0</TD>
    <TD>51.0</TD>
    <TD>233.0</TD>
    <TD>310.0</TD>
    <TD>164.0</TD>
    <TD>0.0</TD>
    <TD>-23.0</TD>
    <TD>282.0</TD>
  </TR>
  <TR>
    <TD>8631</TD>
    <TD>2004-04-10T03:54:07</TD>
    <TD>347.0</TD>
    <TD>35.0</TD>
    <TD>250.0</TD>
    <TD>281.0</TD>
    <TD>217.0</TD>
    <TD>147.0</TD>
    <TD>-2.6</TD>
    <TD>351.0</TD>
  </TR>
  <TR>
    <TD>8632</TD>
    <TD>2004-04-10T08:06:05</TD>
    <TD>241.0</TD>
    <TD>30.0</TD>
    <TD>595.0</TD>
    <TD>513.0</TD>
    <TD>677.0</TD>
    <TD>769.0</TD>
    <TD>13.6</TD>
    <TD>244.0</TD>
  </TR>
  <TR>
    <TD>8633</TD>
    <TD>2004-04-10T17:54:05</TD>
    <TD>217.0</TD>
    <TD>19.0</TD>
    <TD>476.0</TD>
    <TD>544.0</TD>
    <TD>408.0</TD>
    <TD>0.0</TD>
    <TD>-13.5</TD>
    <TD>214.0</TD>
  </TR>
  <TR>
    <TD>8634</TD>
    <TD>2004-04-10T18:54:05</TD>
    <TD>222.0</TD>
    <TD>53.0</TD>
    <TD>311.0</TD>
    <TD>289.0</TD>
    <TD>335.0</TD>
    <TD>397.0</TD>
    <TD>3.1</TD>
    <TD>220.0</TD>
  </TR>
  <TR>
    <TD>8635</TD>
    <TD>2004-04-10T23:06:53</TD>
    <TD>60.0</TD>
    <TD>59.0</TD>
    <TD>607.0</TD>
    <TD>835.0</TD>
    <TD>362.0</TD>
    <TD>459.0</TD>
    <TD>-21.4</TD>
    <TD>65.0</TD>
  </TR>
  <TR>
    <TD>8636</TD>
    <TD>2004-04-11T01:31:42</TD>
    <TD>10.0</TD>
    <TD>37.0</TD>
    <TD>484.0</TD>
    <TD>511.0</TD>
    <TD>457.0</TD>
    <TD>0.0</TD>
    <TD>-15.7</TD>
    <TD>14.0</TD>
  </TR>
  <TR>
    <TD>8637</TD>
    <TD>2004-04-11T04:30:06</TD>
    <TD>203.0</TD>
    <TD>314.0</TD>
    <TD>1645.0</TD>
    <TD>1953.0</TD>
    <TD>1340.0</TD>
    <TD>1474.0</TD>
    <TD>-77.6</TD>
    <TD>237.0</TD>
  </TR>
  <TR>
    <TD>8638</TD>
    <TD>2004-04-11T11:54:05</TD>
    <TD>-1.0</TD>
    <TD>360.0</TD>
    <TD>1132.0</TD>
    <TD>1276.0</TD>
    <TD>972.0</TD>
    <TD>1086.0</TD>
    <TD>-19.4</TD>
    <TD>295.0</TD>
  </TR>
  <TR>
    <TD>8639</TD>
    <TD>2004-04-11T20:30:05</TD>
    <TD>119.0</TD>
    <TD>12.0</TD>
    <TD>465.0</TD>
    <TD>370.0</TD>
    <TD>554.0</TD>
    <TD>739.0</TD>
    <TD>17.3</TD>
    <TD>117.0</TD>
  </TR>
  <TR>
    <TD>8640</TD>
    <TD>2004-04-11T23:30:05</TD>
    <TD>227.0</TD>
    <TD>27.0</TD>
    <TD>670.0</TD>
    <TD>775.0</TD>
    <TD>561.0</TD>
    <TD>0.0</TD>
    <TD>-49.1</TD>
    <TD>227.0</TD>
  </TR>
  <TR>
    <TD>8641</TD>
    <TD>2004-04-12T00:30:05</TD>
    <TD>120.0</TD>
    <TD>16.0</TD>
    <TD>488.0</TD>
    <TD>713.0</TD>
    <TD>277.0</TD>
    <TD>0.0</TD>
    <TD>-118.0</TD>
    <TD>117.0</TD>
  </TR>
  <TR>
    <TD>8642</TD>
    <TD>2004-04-12T00:54:05</TD>
    <TD>248.0</TD>
    <TD>57.0</TD>
    <TD>261.0</TD>
    <TD>262.0</TD>
    <TD>259.0</TD>
    <TD>257.0</TD>
    <TD>-0.1</TD>
    <TD>238.0</TD>
  </TR>
  <TR>
    <TD>8643</TD>
    <TD>2004-04-12T09:54:31</TD>
    <TD>228.0</TD>
    <TD>31.0</TD>
    <TD>537.0</TD>
    <TD>667.0</TD>
    <TD>398.0</TD>
    <TD>0.0</TD>
    <TD>-31.0</TD>
    <TD>235.0</TD>
  </TR>
  <TR>
    <TD>8644</TD>
    <TD>2004-04-12T11:06:05</TD>
    <TD>98.0</TD>
    <TD>21.0</TD>
    <TD>453.0</TD>
    <TD>440.0</TD>
    <TD>466.0</TD>
    <TD>505.0</TD>
    <TD>2.6</TD>
    <TD>101.0</TD>
  </TR>
  <TR>
    <TD>8645</TD>
    <TD>2004-04-12T12:54:05</TD>
    <TD>33.0</TD>
    <TD>50.0</TD>
    <TD>435.0</TD>
    <TD>387.0</TD>
    <TD>483.0</TD>
    <TD>578.0</TD>
    <TD>8.3</TD>
    <TD>39.0</TD>
  </TR>
  <TR>
    <TD>8646</TD>
    <TD>2004-04-12T20:30:06</TD>
    <TD>305.0</TD>
    <TD>44.0</TD>
    <TD>495.0</TD>
    <TD>367.0</TD>
    <TD>615.0</TD>
    <TD>1033.0</TD>
    <TD>39.0</TD>
    <TD>305.0</TD>
  </TR>
  <TR>
    <TD>8647</TD>
    <TD>2004-04-12T21:30:05</TD>
    <TD>100.0</TD>
    <TD>32.0</TD>
    <TD>510.0</TD>
    <TD>472.0</TD>
    <TD>549.0</TD>
    <TD>640.0</TD>
    <TD>8.0</TD>
    <TD>101.0</TD>
  </TR>
  <TR>
    <TD>8648</TD>
    <TD>2004-04-13T05:54:22</TD>
    <TD>58.0</TD>
    <TD>61.0</TD>
    <TD>433.0</TD>
    <TD>432.0</TD>
    <TD>435.0</TD>
    <TD>434.0</TD>
    <TD>0.1</TD>
    <TD>66.0</TD>
  </TR>
  <TR>
    <TD>8649</TD>
    <TD>2004-04-13T08:54:05</TD>
    <TD>309.0</TD>
    <TD>63.0</TD>
    <TD>406.0</TD>
    <TD>408.0</TD>
    <TD>405.0</TD>
    <TD>405.0</TD>
    <TD>-0.1</TD>
    <TD>315.0</TD>
  </TR>
  <TR>
    <TD>8650</TD>
    <TD>2004-04-13T10:54:05</TD>
    <TD>147.0</TD>
    <TD>32.0</TD>
    <TD>458.0</TD>
    <TD>462.0</TD>
    <TD>453.0</TD>
    <TD>449.0</TD>
    <TD>-0.5</TD>
    <TD>150.0</TD>
  </TR>
  <TR>
    <TD>8651</TD>
    <TD>2004-04-13T11:30:05</TD>
    <TD>229.0</TD>
    <TD>39.0</TD>
    <TD>826.0</TD>
    <TD>890.0</TD>
    <TD>768.0</TD>
    <TD>668.0</TD>
    <TD>-14.9</TD>
    <TD>227.0</TD>
  </TR>
  <TR>
    <TD>8652</TD>
    <TD>2004-04-13T18:26:05</TD>
    <TD>320.0</TD>
    <TD>51.0</TD>
    <TD>293.0</TD>
    <TD>364.0</TD>
    <TD>217.0</TD>
    <TD>0.0</TD>
    <TD>-8.5</TD>
    <TD>329.0</TD>
  </TR>
  <TR>
    <TD>8653</TD>
    <TD>2004-04-13T20:59:06</TD>
    <TD>202.0</TD>
    <TD>125.0</TD>
    <TD>325.0</TD>
    <TD>225.0</TD>
    <TD>439.0</TD>
    <TD>411.0</TD>
    <TD>5.0</TD>
    <TD>222.0</TD>
  </TR>
  <TR>
    <TD>8654</TD>
    <TD>2004-04-14T01:27:13</TD>
    <TD>147.0</TD>
    <TD>36.0</TD>
    <TD>380.0</TD>
    <TD>431.0</TD>
    <TD>330.0</TD>
    <TD>0.0</TD>
    <TD>-20.0</TD>
    <TD>145.0</TD>
  </TR>
  <TR>
    <TD>8655</TD>
    <TD>2004-04-14T02:26:05</TD>
    <TD>21.0</TD>
    <TD>135.0</TD>
    <TD>254.0</TD>
    <TD>0.0</TD>
    <TD>559.0</TD>
    <TD>455.0</TD>
    <TD>9.1</TD>
    <TD>52.0</TD>
  </TR>
  <TR>
    <TD>8656</TD>
    <TD>2004-04-14T16:26:05</TD>
    <TD>224.0</TD>
    <TD>27.0</TD>
    <TD>597.0</TD>
    <TD>657.0</TD>
    <TD>536.0</TD>
    <TD>0.0</TD>
    <TD>-18.9</TD>
    <TD>223.0</TD>
  </TR>
  <TR>
    <TD>8657</TD>
    <TD>2004-04-14T18:50:05</TD>
    <TD>107.0</TD>
    <TD>19.0</TD>
    <TD>286.0</TD>
    <TD>211.0</TD>
    <TD>365.0</TD>
    <TD>913.0</TD>
    <TD>33.4</TD>
    <TD>110.0</TD>
  </TR>
  <TR>
    <TD>8658</TD>
    <TD>2004-04-14T20:26:05</TD>
    <TD>170.0</TD>
    <TD>14.0</TD>
    <TD>609.0</TD>
    <TD></TD>
    <TD></TD>
    <TD></TD>
    <TD></TD>
    <TD>170.0</TD>
  </TR>
  <TR>
    <TD>8659</TD>
    <TD>2004-04-14T22:26:05</TD>
    <TD>231.0</TD>
    <TD>43.0</TD>
    <TD>898.0</TD>
    <TD>1334.0</TD>
    <TD>454.0</TD>
    <TD>637.0</TD>
    <TD>-60.2</TD>
    <TD>233.0</TD>
  </TR>
  <TR>
    <TD>8660</TD>
    <TD>2004-04-14T23:06:06</TD>
    <TD>48.0</TD>
    <TD>47.0</TD>
    <TD>524.0</TD>
    <TD>31.0</TD>
    <TD>930.0</TD>
    <TD>822.0</TD>
    <TD>28.6</TD>
    <TD>42.0</TD>
  </TR>
  <TR>
    <TD>8661</TD>
    <TD>2004-04-15T03:26:05</TD>
    <TD>233.0</TD>
    <TD>45.0</TD>
    <TD>714.0</TD>
    <TD>790.0</TD>
    <TD>636.0</TD>
    <TD>648.0</TD>
    <TD>-8.6</TD>
    <TD>232.0</TD>
  </TR>
  <TR>
    <TD>8662</TD>
    <TD>2004-04-15T08:06:05</TD>
    <TD>228.0</TD>
    <TD>39.0</TD>
    <TD>568.0</TD>
    <TD>729.0</TD>
    <TD>384.0</TD>
    <TD>408.0</TD>
    <TD>-15.2</TD>
    <TD>225.0</TD>
  </TR>
  <TR>
    <TD>8663</TD>
    <TD>2004-04-15T08:06:05</TD>
    <TD>308.0</TD>
    <TD>54.0</TD>
    <TD>325.0</TD>
    <TD>316.0</TD>
    <TD>334.0</TD>
    <TD>348.0</TD>
    <TD>0.9</TD>
    <TD>309.0</TD>
  </TR>
  <TR>
    <TD>8664</TD>
    <TD>2004-04-15T17:26:05</TD>
    <TD>280.0</TD>
    <TD>32.0</TD>
    <TD>276.0</TD>
    <TD>118.0</TD>
    <TD>433.0</TD>
    <TD>1033.0</TD>
    <TD>44.2</TD>
    <TD>280.0</TD>
  </TR>
  <TR>
    <TD>8665</TD>
    <TD>2004-04-15T20:26:05</TD>
    <TD>120.0</TD>
    <TD>80.0</TD>
    <TD>489.0</TD>
    <TD>556.0</TD>
    <TD>424.0</TD>
    <TD>0.0</TD>
    <TD>-37.7</TD>
    <TD>110.0</TD>
  </TR>
  <TR>
    <TD>8666</TD>
    <TD>2004-04-16T17:42:06</TD>
    <TD>224.0</TD>
    <TD>29.0</TD>
    <TD>376.0</TD>
    <TD>420.0</TD>
    <TD>334.0</TD>
    <TD>0.0</TD>
    <TD>-24.0</TD>
    <TD>223.0</TD>
  </TR>
  <TR>
    <TD>8667</TD>
    <TD>2004-04-16T18:42:05</TD>
    <TD>96.0</TD>
    <TD>19.0</TD>
    <TD>279.0</TD>
    <TD>224.0</TD>
    <TD>340.0</TD>
    <TD>762.0</TD>
    <TD>22.6</TD>
    <TD>95.0</TD>
  </TR>
  <TR>
    <TD>8668</TD>
    <TD>2004-04-16T18:42:05</TD>
    <TD>40.0</TD>
    <TD>27.0</TD>
    <TD>399.0</TD>
    <TD>525.0</TD>
    <TD>262.0</TD>
    <TD>0.0</TD>
    <TD>-36.8</TD>
    <TD>42.0</TD>
  </TR>
  <TR>
    <TD>8669</TD>
    <TD>2004-04-18T00:42:05</TD>
    <TD>301.0</TD>
    <TD>42.0</TD>
    <TD>185.0</TD>
    <TD>183.0</TD>
    <TD>187.0</TD>
    <TD>208.0</TD>
    <TD>0.4</TD>
    <TD>309.0</TD>
  </TR>
  <TR>
    <TD>8670</TD>
    <TD>2004-04-18T04:42:05</TD>
    <TD>93.0</TD>
    <TD>18.0</TD>
    <TD>340.0</TD>
    <TD>331.0</TD>
    <TD>350.0</TD>
    <TD>444.0</TD>
    <TD>3.7</TD>
    <TD>89.0</TD>
  </TR>
  <TR>
    <TD>8671</TD>
    <TD>2004-04-18T14:08:07</TD>
    <TD>278.0</TD>
    <TD>43.0</TD>
    <TD>310.0</TD>
    <TD>76.0</TD>
    <TD>554.0</TD>
    <TD>1713.0</TD>
    <TD>132.8</TD>
    <TD>268.0</TD>
  </TR>
  <TR>
    <TD>8672</TD>
    <TD>2004-04-18T16:42:05</TD>
    <TD>252.0</TD>
    <TD>51.0</TD>
    <TD>138.0</TD>
    <TD>211.0</TD>
    <TD>64.0</TD>
    <TD>0.0</TD>
    <TD>-13.1</TD>
    <TD>260.0</TD>
  </TR>
  <TR>
    <TD>8673</TD>
    <TD>2004-04-19T02:08:05</TD>
    <TD>266.0</TD>
    <TD>61.0</TD>
    <TD>341.0</TD>
    <TD>350.0</TD>
    <TD>332.0</TD>
    <TD>251.0</TD>
    <TD>-2.5</TD>
    <TD>290.0</TD>
  </TR>
  <TR>
    <TD>8674</TD>
    <TD>2004-04-19T21:08:06</TD>
    <TD>80.0</TD>
    <TD>55.0</TD>
    <TD>812.0</TD>
    <TD></TD>
    <TD></TD>
    <TD></TD>
    <TD></TD>
    <TD>61.0</TD>
  </TR>
  <TR>
    <TD>8675</TD>
    <TD>2004-04-20T02:08:06</TD>
    <TD>183.0</TD>
    <TD>61.0</TD>
    <TD>381.0</TD>
    <TD>294.0</TD>
    <TD>471.0</TD>
    <TD>1121.0</TD>
    <TD>49.2</TD>
    <TD>182.0</TD>
  </TR>
  <TR>
    <TD>8676</TD>
    <TD>2004-04-20T05:42:05</TD>
    <TD>223.0</TD>
    <TD>120.0</TD>
    <TD>335.0</TD>
    <TD>283.0</TD>
    <TD>391.0</TD>
    <TD>363.0</TD>
    <TD>2.1</TD>
    <TD>237.0</TD>
  </TR>
  <TR>
    <TD>8677</TD>
    <TD>2004-04-20T10:08:05</TD>
    <TD>94.0</TD>
    <TD>31.0</TD>
    <TD>315.0</TD>
    <TD>291.0</TD>
    <TD>339.0</TD>
    <TD>539.0</TD>
    <TD>8.6</TD>
    <TD>91.0</TD>
  </TR>
  <TR>
    <TD>8678</TD>
    <TD>2004-04-20T10:08:05</TD>
    <TD>296.0</TD>
    <TD>98.0</TD>
    <TD>248.0</TD>
    <TD>176.0</TD>
    <TD>323.0</TD>
    <TD>296.0</TD>
    <TD>2.3</TD>
    <TD>311.0</TD>
  </TR>
  <TR>
    <TD>8679</TD>
    <TD>2004-04-29T19:27:14</TD>
    <TD>-1.0</TD>
    <TD>360.0</TD>
    <TD>185.0</TD>
    <TD>199.0</TD>
    <TD>168.0</TD>
    <TD>150.0</TD>
    <TD>-0.7</TD>
    <TD>205.0</TD>
  </TR>
  <TR>
    <TD>8680</TD>
    <TD>2004-04-30T04:50:05</TD>
    <TD>317.0</TD>
    <TD>84.0</TD>
    <TD>312.0</TD>
    <TD>387.0</TD>
    <TD>232.0</TD>
    <TD>0.0</TD>
    <TD>-8.6</TD>
    <TD>314.0</TD>
  </TR>
</TABLEDATA>
</DATA>
</TABLE>
</RESOURCE>
</VOTABLE>
